[{"author":"奇舞精选","site":"https://juejin.cn/user/4388906147515367","tag":"前端","article":{"title":"2023款ECMAScript","link":"https://juejin.cn/post/7235966417563992122","date":1684758325000}},{"author":"高级前端进阶","site":"https://www.cimidata.com/a/4QkNDBja","tag":"前端","article":{"title":"揭秘 JavaScript 代码整洁技巧，让你的项目更出众","link":"https://mp.weixin.qq.com/s?__biz=MzA4Nzg0MDM5Nw==&mid=2247517749&idx=1&sn=05c39f2070815362919c6899d5d5da42","date":1684717814000}},{"author":"前端达人","site":"https://www.cimidata.com/a/PQDGAejW","tag":"前端","article":{"title":"分享 21 个简单实用的 JS 代码技巧","link":"https://mp.weixin.qq.com/s?__biz=MjM5MjU2NDk0Nw==&mid=2247509760&idx=1&sn=0c568c763140fcad74c44a937350bb64","date":1684713740000}},{"author":"前端达人","site":"https://www.cimidata.com/a/PQDGAejW","tag":"前端","article":{"title":"简单的聊一聊 async/await 到底要不要加 try catch？","link":"https://mp.weixin.qq.com/s?__biz=MjM5MjU2NDk0Nw==&mid=2247509760&idx=2&sn=395fb9b90c4224cdffd2239d9fd4db8e","date":1684713740000}},{"author":"前端大全","site":"https://www.cimidata.com/a/nqQBNbQz","tag":"前端","article":{"title":"放心，前端死不了","link":"https://mp.weixin.qq.com/s?__biz=MzAxODE2MjM1MA==&mid=2651614613&idx=1&sn=a4b6f0d414dda054260aed27446f2822","date":1684727433000}},{"author":"前端大全","site":"https://www.cimidata.com/a/nqQBNbQz","tag":"前端","article":{"title":"肝完《浏览器基本原理与实践》后，我总结了这 36 点","link":"https://mp.weixin.qq.com/s?__biz=MzAxODE2MjM1MA==&mid=2651614613&idx=2&sn=a9e34f2237a9f6faa7832e1e8a800a3e","date":1684727433000}},{"author":"前端之巅","site":"https://www.cimidata.com/a/1rQA9VQZ","tag":"前端","article":{"title":"React JS广受业界认可，高级开发者年薪百万","link":"https://mp.weixin.qq.com/s?__biz=MzUxMzcxMzE5Ng==&mid=2247520936&idx=1&sn=22e6082f72240a6fc13e315a7712b47f","date":1684738867000}},{"author":"前端自习课","site":"https://www.cimidata.com/a/813oWw3l","tag":"前端","article":{"title":"群内疯传！前端45K面经，堪称涨薪天花板！","link":"https://mp.weixin.qq.com/s?__biz=MjM5MDc4MzgxNA==&mid=2458470927&idx=1&sn=e161afbad49253482461db0ecaf52f76","date":1684722030000}},{"author":"前端自习课","site":"https://www.cimidata.com/a/813oWw3l","tag":"前端","article":{"title":"【总结】1690- 一些常见的移动端适配方案，你了解吗？","link":"https://mp.weixin.qq.com/s?__biz=MjM5MDc4MzgxNA==&mid=2458470927&idx=2&sn=01ffdd19d0be96d2c06476e2366f086c","date":1684722030000}},{"author":"前端瓶子君","site":"https://www.cimidata.com/a/Vj5ZdDQn","tag":"前端","article":{"title":"放心，前端死不了","link":"https://mp.weixin.qq.com/s?__biz=MzUzNjk5MTE1OQ==&mid=2247521166&idx=1&sn=e6093a6a47619331206e0cb991334d33","date":1684716603000}}]