[{"author":"政采云前端团队","site":"https://juejin.cn/user/3456520257288974","tag":"前端","article":{"title":"Java线程和CPU调度","link":"https://juejin.cn/post/7295669711533817893","date":1698715845000}},{"author":"奇舞精选","site":"https://juejin.cn/user/4388906147515367","tag":"前端","article":{"title":"【译】CSS Animations 与 CSS Transitions","link":"https://juejin.cn/post/7295954109404004403","date":1698747693000}},{"author":"高级前端进阶","site":"https://www.cimidata.com/a/4QkNDBja","tag":"前端","article":{"title":"今年这情况。。。多一个选择吧","link":"https://mp.weixin.qq.com/s?__biz=MzA4Nzg0MDM5Nw==&mid=2247519046&idx=1&sn=6d23e7c1aa72021d175b85a774318f49","date":1698718851000}},{"author":"高级前端进阶","site":"https://www.cimidata.com/a/4QkNDBja","tag":"前端","article":{"title":"前端技术发展趋势","link":"https://mp.weixin.qq.com/s?__biz=MzA4Nzg0MDM5Nw==&mid=2247519046&idx=2&sn=5f8d04f4d559aa5f139958d1422925ed","date":1698718851000}},{"author":"前端达人","site":"https://www.cimidata.com/a/PQDGAejW","tag":"前端","article":{"title":"什么样的开发，会被公司抢着要？","link":"https://mp.weixin.qq.com/s?__biz=MjM5MjU2NDk0Nw==&mid=2247513926&idx=1&sn=76e74596232fbc1fa349075219bf8acc","date":1698718835000}},{"author":"前端达人","site":"https://www.cimidata.com/a/PQDGAejW","tag":"前端","article":{"title":"聊一聊如何在 Vue3 表单中显示和隐藏元素","link":"https://mp.weixin.qq.com/s?__biz=MjM5MjU2NDk0Nw==&mid=2247513926&idx=2&sn=3a8ef1285491c7e0e6c0677918ef7a28","date":1698718835000}},{"author":"前端大全","site":"https://www.cimidata.com/a/nqQBNbQz","tag":"前端","article":{"title":"这些天，我们前端组一起处理的项目优化","link":"https://mp.weixin.qq.com/s?__biz=MzAxODE2MjM1MA==&mid=2651617386&idx=1&sn=d3ef410baee45ee82be55d3eeaee5f2d","date":1698724234000}},{"author":"前端大全","site":"https://www.cimidata.com/a/nqQBNbQz","tag":"前端","article":{"title":"用代码聊聊我们跟目前主流前端编程不一样的地方","link":"https://mp.weixin.qq.com/s?__biz=MzAxODE2MjM1MA==&mid=2651617386&idx=2&sn=93a3ef6fa22435507bf0b274f489c327","date":1698724234000}},{"author":"前端自习课","site":"https://www.cimidata.com/a/813oWw3l","tag":"前端","article":{"title":"【资讯】1851- Next.js 14 正式发布，更快、更强、更可靠！","link":"https://mp.weixin.qq.com/s?__biz=MjM5MDc4MzgxNA==&mid=2458472584&idx=2&sn=e463d35071b2cd4c292ff6df2ab29ce7","date":1698718845000}},{"author":"前端自习课","site":"https://www.cimidata.com/a/813oWw3l","tag":"前端","article":{"title":"Vue3在今年面试中火到离谱！","link":"https://mp.weixin.qq.com/s?__biz=MjM5MDc4MzgxNA==&mid=2458472584&idx=1&sn=50bcafaf3dfb627b3dd3ea522e68e3f5","date":1698718845000}},{"author":"前端瓶子君","site":"https://www.cimidata.com/a/Vj5ZdDQn","tag":"前端","article":{"title":"前端面试题之性能优化大杂烩","link":"https://mp.weixin.qq.com/s?__biz=MzUzNjk5MTE1OQ==&mid=2247522118&idx=1&sn=6e2cd7095279528b6a85f2b1bb75076f","date":1698713117000}}]